woodwork/__init__.py
woodwork/accessor_utils.py
woodwork/column_accessor.py
woodwork/column_schema.py
woodwork/config.py
woodwork/deserialize.py
woodwork/exceptions.py
woodwork/indexers.py
woodwork/logical_types.py
woodwork/s3_utils.py
woodwork/table_accessor.py
woodwork/table_schema.py
woodwork/typing.py
woodwork/utils.py
woodwork/version.py
woodwork/data/1-1000.txt
woodwork/data/__init__.py
woodwork/demo/__init__.py
woodwork/demo/api.py
woodwork/demo/retail.py
woodwork/deserializers/__init__.py
woodwork/deserializers/arrow_deserializer.py
woodwork/deserializers/csv_deserializer.py
woodwork/deserializers/deserializer_base.py
woodwork/deserializers/feather_deserializer.py
woodwork/deserializers/orc_deserializer.py
woodwork/deserializers/parquet_deserializer.py
woodwork/deserializers/pickle_deserializer.py
woodwork/deserializers/utils.py
woodwork/serializers/__init__.py
woodwork/serializers/arrow_serializer.py
woodwork/serializers/csv_serializer.py
woodwork/serializers/feather_serializer.py
woodwork/serializers/orc_serializer.py
woodwork/serializers/parquet_serializer.py
woodwork/serializers/pickle_serializer.py
woodwork/serializers/serializer_base.py
woodwork/serializers/utils.py
woodwork/statistics_utils/__init__.py
woodwork/statistics_utils/_bin_numeric_cols_into_categories.py
woodwork/statistics_utils/_calculate_dependence_measure.py
woodwork/statistics_utils/_calculate_max_dependence_for_pair.py
woodwork/statistics_utils/_cast_nullable_int_and_datetime_to_int.py
woodwork/statistics_utils/_convert_ordinal_to_numeric.py
woodwork/statistics_utils/_get_box_plot_info_for_column.py
woodwork/statistics_utils/_get_dependence_dict.py
woodwork/statistics_utils/_get_describe_dict.py
woodwork/statistics_utils/_get_histogram_values.py
woodwork/statistics_utils/_get_medcouple_statistic.py
woodwork/statistics_utils/_get_mode.py
woodwork/statistics_utils/_get_numeric_value_counts_in_range.py
woodwork/statistics_utils/_get_recent_value_counts.py
woodwork-0.31.0.dist-info/LICENSE
woodwork-0.31.0.dist-info/METADATA
woodwork-0.31.0.dist-info/WHEEL
woodwork-0.31.0.dist-info/top_level.txt
woodwork-0.31.0.dist-info/RECORD
