Metadata-Version: 2.1
Name: woodwork
Version: 0.31.0
Summary: a data typing library for machine learning
Author-email: "Alteryx, Inc." <open_source_support@alteryx.com>
Maintainer-email: "Alteryx, Inc." <open_source_support@alteryx.com>
License: BSD 3-Clause License
Project-URL: Documentation, https://woodwork.alteryx.com
Project-URL: Source Code, https://github.com/alteryx/woodwork/
Project-URL: Changes, https://woodwork.alteryx.com/en/latest/release_notes.html
Project-URL: Issue Tracker, https://github.com/alteryx/woodwork/issues
Project-URL: Twitter, https://twitter.com/alteryxoss
Project-URL: Chat, https://join.slack.com/t/alteryx-oss/shared_invite/zt-182tyvuxv-NzIn6eiCEf8TBziuKp0bNA
Keywords: data science,machine learning,typing
Classifier: Development Status :: 3 - Alpha
Classifier: Intended Audience :: Science/Research
Classifier: Intended Audience :: Developers
Classifier: Topic :: Software Development
Classifier: Topic :: Scientific/Engineering
Classifier: Programming Language :: Python
Classifier: Programming Language :: Python :: 3
Classifier: Programming Language :: Python :: 3.9
Classifier: Programming Language :: Python :: 3.10
Classifier: Programming Language :: Python :: 3.11
Classifier: Programming Language :: Python :: 3.12
Classifier: Operating System :: Microsoft :: Windows
Classifier: Operating System :: POSIX
Classifier: Operating System :: Unix
Classifier: Operating System :: MacOS
Requires-Python: <4,>=3.9
License-File: LICENSE
Requires-Dist: pandas>=2.0.0
Requires-Dist: scikit-learn>=1.1.0
Requires-Dist: python-dateutil>=2.8.2
Requires-Dist: scipy>=1.10.0
Requires-Dist: importlib-resources>=5.10.0
Requires-Dist: numpy>=1.25.0
Provides-Extra: test
Requires-Dist: pytest>=7.0.1; extra == "test"
Requires-Dist: pytest-cov>=2.10.1; extra == "test"
Requires-Dist: pytest-xdist>=2.1.0; extra == "test"
Requires-Dist: boto3>=1.34.32; extra == "test"
Requires-Dist: moto[all]>=5.0.0; extra == "test"
Requires-Dist: smart-open>=5.0.0; extra == "test"
Requires-Dist: pyarrow>=14.0.1; extra == "test"
Provides-Extra: updater
Requires-Dist: alteryx-open-src-update-checker>=3.1.0; extra == "updater"
Provides-Extra: docs
Requires-Dist: Sphinx==5.1.1; extra == "docs"
Requires-Dist: nbsphinx==0.8.9; extra == "docs"
Requires-Dist: pydata-sphinx-theme==0.9.0; extra == "docs"
Requires-Dist: sphinx-inline-tabs==2022.1.2b11; extra == "docs"
Requires-Dist: sphinx-copybutton==0.5.0; extra == "docs"
Requires-Dist: myst-parser==0.18.0; extra == "docs"
Requires-Dist: nbconvert==6.5.0; extra == "docs"
Requires-Dist: ipython==8.4.0; extra == "docs"
Requires-Dist: jupyter==1.0.0; extra == "docs"
Requires-Dist: pyarrow>=14.0.1; extra == "docs"
Provides-Extra: dev
Requires-Dist: ruff>=0.1.6; extra == "dev"
Requires-Dist: pre-commit>=2.20.0; extra == "dev"
Requires-Dist: click>=8.1.7; extra == "dev"
Requires-Dist: woodwork[docs,test]; extra == "dev"
Provides-Extra: complete
Requires-Dist: woodwork[updater]; extra == "complete"
